[
	{
		"albumtitle": "《良院专区》保罗书信 I(01)",
		"title": "認識保羅",
		"duration": 1760,
		"size": "3.5M",
		"albumId": 164,
		"albumName": "《良院专区》保罗书信 I",
		"path": "https://rawcdn.githack.com/quiet324/LiangYouSchoolAlbum11/1706052/mavpi/mavpi001.mp3",
		"id": 164888180
	},
	{
		"albumtitle": "《良院专区》保罗书信 I(02)",
		"title": "保羅書信總論",
		"duration": 1760,
		"size": "3.5M",
		"albumId": 164,
		"albumName": "《良院专区》保罗书信 I",
		"path": "https://rawcdn.githack.com/quiet324/LiangYouSchoolAlbum11/1706052/mavpi/mavpi002.mp3",
		"id": 164888181
	},
	{
		"albumtitle": "《良院专区》保罗书信 I(03)",
		"title": "羅馬書導論",
		"duration": 1760,
		"size": "3.5M",
		"albumId": 164,
		"albumName": "《良院专区》保罗书信 I",
		"path": "https://rawcdn.githack.com/quiet324/LiangYouSchoolAlbum11/1706052/mavpi/mavpi003.mp3",
		"id": 164888182
	},
	{
		"albumtitle": "《良院专区》保罗书信 I(04)",
		"title": "聖潔的神譴責罪惡 羅 1：18 至 3：20 ",
		"duration": 1760,
		"size": "3.5M",
		"albumId": 164,
		"albumName": "《良院专区》保罗书信 I",
		"path": "https://rawcdn.githack.com/quiet324/LiangYouSchoolAlbum11/1706052/mavpi/mavpi004.mp3",
		"id": 164888183
	},
	{
		"albumtitle": "《良院专区》保罗书信 I(05)",
		"title": "神的恩使罪人稱義 羅 3：21 至 5：21 ",
		"duration": 1760,
		"size": "3.5M",
		"albumId": 164,
		"albumName": "《良院专区》保罗书信 I",
		"path": "https://rawcdn.githack.com/quiet324/LiangYouSchoolAlbum11/1706052/mavpi/mavpi005.mp3",
		"id": 164888184
	},
	{
		"albumtitle": "《良院专区》保罗书信 I(06)",
		"title": "神的權能使信徒成聖 羅 6：1 至 8：39",
		"duration": 1760,
		"size": "3.5M",
		"albumId": 164,
		"albumName": "《良院专区》保罗书信 I",
		"path": "https://rawcdn.githack.com/quiet324/LiangYouSchoolAlbum11/1706052/mavpi/mavpi006.mp3",
		"id": 164888185
	}
,
	{
		"albumtitle": "《良院专区》保罗书信 I(07)",
		"title": "洗禮真義 羅 6：3－11",
		"duration": 1760,
		"size": "3.5M",
		"albumId": 164,
		"albumName": "《良院专区》保罗书信 I",
		"path": "https://rawcdn.githack.com/quiet324/LiangYouSchoolAlbum11/1706052/mavpi/mavpi007.mp3",
		"id": 164888186
	},
	{
		"albumtitle": "《良院专区》保罗书信 I(08)",
		"title": "聖靈的工作 羅 8 章",
		"duration": 1760,
		"size": "3.5M",
		"albumId": 164,
		"albumName": "《良院专区》保罗书信 I",
		"path": "https://rawcdn.githack.com/quiet324/LiangYouSchoolAlbum11/1706052/mavpi/mavpi008.mp3",
		"id": 164888187
	},
	{
		"albumtitle": "《良院专区》保罗书信 I(09)",
		"title": "以色列全家得救 羅 9－11 章",
		"duration": 1760,
		"size": "3.5M",
		"albumId": 164,
		"albumName": "《良院专区》保罗书信 I",
		"path": "https://rawcdn.githack.com/quiet324/LiangYouSchoolAlbum11/1706052/mavpi/mavpi009.mp3",
		"id": 164888188
	},
	{
		"albumtitle": "《良院专区》保罗书信 I(10)",
		"title": "獻上身體 羅 12－13 章",
		"duration": 1760,
		"size": "3.5M",
		"albumId": 164,
		"albumName": "《良院专区》保罗书信 I",
		"path": "https://rawcdn.githack.com/quiet324/LiangYouSchoolAlbum11/1706052/mavpi/mavpi010.mp3",
		"id": 164888189
	},
	{
		"albumtitle": "《良院专区》保罗书信 I(11)",
		"title": "行事為人的原則 羅 14：1 至 15：13 ",
		"duration": 1760,
		"size": "3.5M",
		"albumId": 164,
		"albumName": "《良院专区》保罗书信 I",
		"path": "https://rawcdn.githack.com/quiet324/LiangYouSchoolAlbum11/1706052/mavpi/mavpi011.mp3",
		"id": 164888190
	},
	{
		"albumtitle": "《良院专区》保罗书信 I(12)",
		"title": "保羅述職 羅 15：14 至 16 章",
		"duration": 1760,
		"size": "3.5M",
		"albumId": 164,
		"albumName": "《良院专区》保罗书信 I",
		"path": "https://rawcdn.githack.com/quiet324/LiangYouSchoolAlbum11/1706052/mavpi/mavpi012.mp3",
		"id": 164888191
	},
	{
		"albumtitle": "《良院专区》保罗书信 I(13)",
		"title": "哥林多前書導論",
		"duration": 1760,
		"size": "3.5M",
		"albumId": 164,
		"albumName": "《良院专区》保罗书信 I",
		"path": "https://rawcdn.githack.com/quiet324/LiangYouSchoolAlbum11/1706052/mavpi/mavpi013.mp3",
		"id": 164888192
	},
	{
		"albumtitle": "《良院专区》保罗书信 I(14)",
		"title": "論教會的紛爭 林前 1－6 章",
		"duration": 1760,
		"size": "3.5M",
		"albumId": 164,
		"albumName": "《良院专区》保罗书信 I",
		"path": "https://rawcdn.githack.com/quiet324/LiangYouSchoolAlbum11/1706052/mavpi/mavpi014.mp3",
		"id": 164888193
	},
	{
		"albumtitle": "《良院专区》保罗书信 I(15)",
		"title": "論福音的中心 林前 1－4 章",
		"duration": 1760,
		"size": "3.5M",
		"albumId": 164,
		"albumName": "《良院专区》保罗书信 I",
		"path": "https://rawcdn.githack.com/quiet324/LiangYouSchoolAlbum11/1706052/mavpi/mavpi015.mp3",
		"id": 164888194
	},
	{
		"albumtitle": "《良院专区》保罗书信 I(16)",
		"title": "論婚姻的問題 林前 7 章",
		"duration": 1760,
		"size": "3.5M",
		"albumId": 164,
		"albumName": "《良院专区》保罗书信 I",
		"path": "https://rawcdn.githack.com/quiet324/LiangYouSchoolAlbum11/1706052/mavpi/mavpi016.mp3",
		"id": 164888195
	}
,
	{
		"albumtitle": "《良院专区》保罗书信 I(17)",
		"title": "論祭偶像之物 林前 8－10 章",
		"duration": 1760,
		"size": "3.5M",
		"albumId": 164,
		"albumName": "《良院专区》保罗书信 I",
		"path": "https://rawcdn.githack.com/quiet324/LiangYouSchoolAlbum11/1706052/mavpi/mavpi017.mp3",
		"id": 164888196
	},
	{
		"albumtitle": "《良院专区》保罗书信 I(18)",
		"title": "論崇拜次序 林前 11 章",
		"duration": 1760,
		"size": "3.5M",
		"albumId": 164,
		"albumName": "《良院专区》保罗书信 I",
		"path": "https://rawcdn.githack.com/quiet324/LiangYouSchoolAlbum11/1706052/mavpi/mavpi018.mp3",
		"id": 164888197
	},
	{
		"albumtitle": "《良院专区》保罗书信 I(19)",
		"title": "論屬靈恩賜 林前 12－13 章",
		"duration": 1760,
		"size": "3.5M",
		"albumId": 164,
		"albumName": "《良院专区》保罗书信 I",
		"path": "https://rawcdn.githack.com/quiet324/LiangYouSchoolAlbum11/1706052/mavpi/mavpi019.mp3",
		"id": 164888198
	},
	{
		"albumtitle": "《良院专区》保罗书信 I(20)",
		"title": "論方言與先知講道 林前 14 章",
		"duration": 1760,
		"size": "3.5M",
		"albumId": 164,
		"albumName": "《良院专区》保罗书信 I",
		"path": "https://rawcdn.githack.com/quiet324/LiangYouSchoolAlbum11/1706052/mavpi/mavpi020.mp3",
		"id": 164888199
	},
	{
		"albumtitle": "《良院专区》保罗书信 I(21)",
		"title": "論基督復活 林前 15 章",
		"duration": 1760,
		"size": "3.5M",
		"albumId": 164,
		"albumName": "《良院专区》保罗书信 I",
		"path": "https://rawcdn.githack.com/quiet324/LiangYouSchoolAlbum11/1706052/mavpi/mavpi021.mp3",
		"id": 164888200
	},
	{
		"albumtitle": "《良院专区》保罗书信 I(22)",
		"title": "哥林多后書導論",
		"duration": 1760,
		"size": "3.5M",
		"albumId": 164,
		"albumName": "《良院专区》保罗书信 I",
		"path": "https://rawcdn.githack.com/quiet324/LiangYouSchoolAlbum11/1706052/mavpi/mavpi022.mp3",
		"id": 164888201
	},
	{
		"albumtitle": "《良院专区》保罗书信 I(23)",
		"title": "服侍中的艱難與神的恩賜 林后 1－7 章",
		"duration": 1760,
		"size": "3.5M",
		"albumId": 164,
		"albumName": "《良院专区》保罗书信 I",
		"path": "https://rawcdn.githack.com/quiet324/LiangYouSchoolAlbum11/1706052/mavpi/mavpi023.mp3",
		"id": 164888202
	},
	{
		"albumtitle": "《良院专区》保罗书信 I(24)",
		"title": "在捐助中表明神的恩典 林后 8－9 章",
		"duration": 1760,
		"size": "3.5M",
		"albumId": 164,
		"albumName": "《良院专区》保罗书信 I",
		"path": "https://rawcdn.githack.com/quiet324/LiangYouSchoolAlbum11/1706052/mavpi/mavpi024.mp3",
		"id": 164888203
	},
	{
		"albumtitle": "《良院专区》保罗书信 I(25)",
		"title": "服侍的憑據與神夠用的恩典 林后 10－13 章",
		"duration": 1760,
		"size": "3.5M",
		"albumId": 164,
		"albumName": "《良院专区》保罗书信 I",
		"path": "https://rawcdn.githack.com/quiet324/LiangYouSchoolAlbum11/1706052/mavpi/mavpi025.mp3",
		"id": 164888204
	},
	{
		"albumtitle": "《良院专区》保罗书信 I(26)",
		"title": "加拉太書導論",
		"duration": 1760,
		"size": "3.5M",
		"albumId": 164,
		"albumName": "《良院专区》保罗书信 I",
		"path": "https://rawcdn.githack.com/quiet324/LiangYouSchoolAlbum11/1706052/mavpi/mavpi026.mp3",
		"id": 164888205
	},
	{
		"albumtitle": "《良院专区》保罗书信 I(27)",
		"title": "從神而來的福音 加 1－2 章",
		"duration": 1760,
		"size": "3.5M",
		"albumId": 164,
		"albumName": "《良院专区》保罗书信 I",
		"path": "https://rawcdn.githack.com/quiet324/LiangYouSchoolAlbum11/1706052/mavpi/mavpi027.mp3",
		"id": 164888206
	},
	{
		"albumtitle": "《良院专区》保罗书信 I(28)",
		"title": "信心與律法的比較 加 3：1－24 ",
		"duration": 1760,
		"size": "3.5M",
		"albumId": 164,
		"albumName": "《良院专区》保罗书信 I",
		"path": "https://rawcdn.githack.com/quiet324/LiangYouSchoolAlbum11/1706052/mavpi/mavpi028.mp3",
		"id": 164888207
	},
	{
		"albumtitle": "《良院专区》保罗书信 I(29)",
		"title": "在基督裡的自由 加 3：25 至 4 章 ",
		"duration": 1760,
		"size": "3.5M",
		"albumId": 164,
		"albumName": "《良院专区》保罗书信 I",
		"path": "https://rawcdn.githack.com/quiet324/LiangYouSchoolAlbum11/1706052/mavpi/mavpi029.mp3",
		"id": 164888208
	},
	{
		"albumtitle": "《良院专区》保罗书信 I(30)",
		"title": "聖靈的福音 加 5－6 章 ",
		"duration": 1760,
		"size": "3.5M",
		"albumId": 164,
		"albumName": "《良院专区》保罗书信 I",
		"path": "https://rawcdn.githack.com/quiet324/LiangYouSchoolAlbum11/1706052/mavpi/mavpi030.mp3",
		"id": 164888209
	}
]