[
	{
		"duration": 2500,
		"size": "7M",
		"path": "https://bbnbi-a.akamaihd.net/BBNBIAudio/Chinese/22301%20LMY%20Look%20forward%20and%20carry%20on.m4a",
		"id": 7037000001,
		"albumId": 7037,
		"albumName": "BBN 22300 基督徒生活讲座--承先启后，继往开来 | 李秀全牧师 ",
		"albumtitle": "BBN 22300 基督徒生活讲座--承先启后，继往开来 | 李秀全牧师 (1)",
		"title": "讲座1 - 22301 基督徒生活讲座--承先启后，继往开来"
	},
	{
		"duration": 2500,
		"size": "7M",
		"path": "https://bbnbi-a.akamaihd.net/BBNBIAudio/Chinese/22302%20LMY%20Look%20forward%20and%20carry%20on.m4a",
		"id": 7037000002,
		"albumId": 7037,
		"albumName": "BBN 22300 基督徒生活讲座--承先启后，继往开来 | 李秀全牧师 ",
		"albumtitle": "BBN 22300 基督徒生活讲座--承先启后，继往开来 | 李秀全牧师 (2)",
		"title": "讲座2 - 22302 基督徒生活讲座--承先启后，继往开来"
	},
	{
		"duration": 2500,
		"size": "7M",
		"path": "https://bbnbi-a.akamaihd.net/BBNBIAudio/Chinese/22303%20LMY%20Look%20forward%20and%20carry%20on.m4a",
		"id": 7037000003,
		"albumId": 7037,
		"albumName": "BBN 22300 基督徒生活讲座--承先启后，继往开来 | 李秀全牧师 ",
		"albumtitle": "BBN 22300 基督徒生活讲座--承先启后，继往开来 | 李秀全牧师 (3)",
		"title": "讲座3 - 22303 基督徒生活讲座--承先启后，继往开来"
	},
	{
		"duration": 2500,
		"size": "7M",
		"path": "https://bbnbi-a.akamaihd.net/BBNBIAudio/Chinese/22304%20LMY%20Look%20forward%20and%20carry%20on.m4a",
		"id": 7037000004,
		"albumId": 7037,
		"albumName": "BBN 22300 基督徒生活讲座--承先启后，继往开来 | 李秀全牧师 ",
		"albumtitle": "BBN 22300 基督徒生活讲座--承先启后，继往开来 | 李秀全牧师 (4)",
		"title": "讲座4 - 22304 基督徒生活讲座--承先启后，继往开来"
	},
	{
		"duration": 2500,
		"size": "7M",
		"path": "https://bbnbi-a.akamaihd.net/BBNBIAudio/Chinese/22305%20LMY%20Look%20forward%20and%20carry%20on.m4a",
		"id": 7037000005,
		"albumId": 7037,
		"albumName": "BBN 22300 基督徒生活讲座--承先启后，继往开来 | 李秀全牧师 ",
		"albumtitle": "BBN 22300 基督徒生活讲座--承先启后，继往开来 | 李秀全牧师 (5)",
		"title": "讲座5 - 22305 基督徒生活讲座--承先启后，继往开来"
	},
	{
		"duration": 2500,
		"size": "7M",
		"path": "https://bbnbi-a.akamaihd.net/BBNBIAudio/Chinese/22306%20LMY%20Look%20forward%20and%20carry%20on.m4a",
		"id": 7037000006,
		"albumId": 7037,
		"albumName": "BBN 22300 基督徒生活讲座--承先启后，继往开来 | 李秀全牧师 ",
		"albumtitle": "BBN 22300 基督徒生活讲座--承先启后，继往开来 | 李秀全牧师 (6)",
		"title": "讲座6 - 22306 基督徒生活讲座--承先启后，继往开来"
	},
	{
		"duration": 2500,
		"size": "7M",
		"path": "https://bbnbi-a.akamaihd.net/BBNBIAudio/Chinese/22307%20LMY%20Look%20forward%20and%20carry%20on.m4a",
		"id": 7037000007,
		"albumId": 7037,
		"albumName": "BBN 22300 基督徒生活讲座--承先启后，继往开来 | 李秀全牧师 ",
		"albumtitle": "BBN 22300 基督徒生活讲座--承先启后，继往开来 | 李秀全牧师 (7)",
		"title": "讲座7 - 22307 基督徒生活讲座--承先启后，继往开来"
	},
	{
		"duration": 2500,
		"size": "7M",
		"path": "https://bbnbi-a.akamaihd.net/BBNBIAudio/Chinese/22308%20%20LMY%20Look%20forward%20and%20carry%201.m4a",
		"id": 7037000008,
		"albumId": 7037,
		"albumName": "BBN 22300 基督徒生活讲座--承先启后，继往开来 | 李秀全牧师 ",
		"albumtitle": "BBN 22300 基督徒生活讲座--承先启后，继往开来 | 李秀全牧师 (8)",
		"title": "讲座8 - 22308 基督徒生活讲座--承先启后，继往开来"
	}
]